syncsign/__init__.py
syncsign/api_helper.py
syncsign/client.py
syncsign/configuration.py
syncsign/decorators.py
syncsign/api/__init__.py
syncsign/api/base_api.py
syncsign/api/devices_api.py
syncsign/api/display_render_api.py
syncsign/api/nodes_api.py
syncsign/api/user_api.py
syncsign/exceptions/__init__.py
syncsign/exceptions/api_exception.py
syncsign/http/__init__.py
syncsign/http/api_response.py
syncsign/http/http_call_back.py
syncsign/http/http_client.py
syncsign/http/http_method_enum.py
syncsign/http/http_request.py
syncsign/http/http_response.py
syncsign/http/requests_client.py
syncsign/http/auth/__init__.py
syncsign/http/auth/o_auth_2.py
syncsign-0.1.0.dist-info/LICENSE
syncsign-0.1.0.dist-info/METADATA
syncsign-0.1.0.dist-info/WHEEL
syncsign-0.1.0.dist-info/top_level.txt
syncsign-0.1.0.dist-info/RECORD
